[{"Category": "[소식]", "Text": "                은하탐구생활——「아글라이아: 누리망 예절을 지키는 건 모두의 책임」|〈붕괴: 스타레일〉               ", "Date": "                  2025/1/29                "}, {"Category": "[소식]", "Text": "                3.0 버전 「재창기의 개선가」 버전 업데이트 안내              ", "Date": "                  2025/1/15                "}, {"Category": "[소식]", "Text": "                 더 헤르타 캐릭터 PV——「우주에는 천재가 있다」|〈붕괴: 스타레일〉              ", "Date": "                  2025/1/14                "}, {"Category": "[소식]", "Text": "                〈붕괴: 스타레일〉 신화의 시작 PV: 「신들의 침묵의 노래」              ", "Date": "                  2025/1/12                "}, {"Category": "[소식]", "Text": "                〈붕괴: 스타레일〉 단편 애니메이션: 「더 헤 르 타 의 마 법 주 방」              ", "Date": "                  2025/1/10                "}]