[{"Category": "[소식]", "Text": "「뛰어난 파트너」 업데이트 안내", "Date": "2025/04/01"}, {"Category": "[소식]", "Text": "〈젠레스 존 제로〉 2025년 4월 달력 월페이퍼", "Date": "2025/04/01"}, {"Category": "[소식]", "Text": "「트리거」 캐릭터 PV 「침식된 눈의 증언」 | 젠레스 존 제로", "Date": "2025/04/01"}, {"Category": "[소식]", "Text": "별빛 기사 EP 「새벽녘 하늘, 빛나는 맹세」 | 젠레스 존 제로", "Date": "2025/04/01"}, {"Category": "[소식]", "Text": "파트너 파일 업데이트 | 주연", "Date": "2025/03/31"}, {"Category": "[소식]", "Text": "신규 스토리: 에이전트 비화 「눈에 닿지 않는」", "Date": "2025/03/31"}, {"Category": "[소식]", "Text": "「어둠 속에서 핀 꽃」 변조 설명", "Date": "2025/03/31"}, {"Category": "[소식]", "Text": "「곧게 발사된 총알」 변조 설명", "Date": "2025/03/31"}]